django_cloudflareimages_toolkit/__init__.py
django_cloudflareimages_toolkit/admin.py
django_cloudflareimages_toolkit/apps.py
django_cloudflareimages_toolkit/exceptions.py
django_cloudflareimages_toolkit/fields.py
django_cloudflareimages_toolkit/models.py
django_cloudflareimages_toolkit/serializers.py
django_cloudflareimages_toolkit/services.py
django_cloudflareimages_toolkit/settings.py
django_cloudflareimages_toolkit/transformations.py
django_cloudflareimages_toolkit/urls.py
django_cloudflareimages_toolkit/views.py
django_cloudflareimages_toolkit/widgets.py
django_cloudflareimages_toolkit/management/__init__.py
django_cloudflareimages_toolkit/management/commands/__init__.py
django_cloudflareimages_toolkit/management/commands/cleanup_expired_images.py
django_cloudflareimages_toolkit/migrations/0001_initial.py
django_cloudflareimages_toolkit/migrations/__init__.py
django_cloudflareimages_toolkit/static/admin/css/cloudflare_images_admin.css
django_cloudflareimages_toolkit/static/admin/js/cloudflare_images_admin.js
django_cloudflareimages_toolkit/templatetags/__init__.py
django_cloudflareimages_toolkit/templatetags/cloudflare_images.py
django_cloudflareimages_toolkit-1.0.9.dist-info/METADATA
django_cloudflareimages_toolkit-1.0.9.dist-info/WHEEL
django_cloudflareimages_toolkit-1.0.9.dist-info/licenses/LICENSE
django_cloudflareimages_toolkit-1.0.9.dist-info/RECORD
