Metadata-Version: 2.4
Name: django-cloudflareimages-toolkit
Version: 1.0.9
Summary: Comprehensive Django toolkit for Cloudflare Images with direct creator upload, transformations, and management
Project-URL: Homepage, https://github.com/Pacficient-Labs/django-cloudflareimages-toolkit
Project-URL: Documentation, https://django-cloudflareimages-toolkit.readthedocs.io/
Project-URL: Repository, https://github.com/Pacficient-Labs/django-cloudflareimages-toolkit.git
Project-URL: Issues, https://github.com/Pacficient-Labs/django-cloudflareimages-toolkit/issues
Author-email: PacNPal <pac@pacnp.al>
License: MIT License
License-File: LICENSE
Keywords: cloudflare,direct-creator,django,images,upload
Classifier: Development Status :: 4 - Beta
Classifier: Environment :: Web Environment
Classifier: Framework :: Django
Classifier: Framework :: Django :: 4.0
Classifier: Framework :: Django :: 4.1
Classifier: Framework :: Django :: 4.2
Classifier: Framework :: Django :: 5.0
Classifier: Intended Audience :: Developers
Classifier: License :: OSI Approved :: MIT License
Classifier: Operating System :: OS Independent
Classifier: Programming Language :: Python
Classifier: Programming Language :: Python :: 3.10
Classifier: Programming Language :: Python :: 3.11
Classifier: Programming Language :: Python :: 3.12
Classifier: Programming Language :: Python :: 3.13
Classifier: Topic :: Internet :: WWW/HTTP
Classifier: Topic :: Software Development :: Libraries :: Python Modules
Requires-Python: >=3.10
Requires-Dist: django>=4.2
Requires-Dist: djangorestframework>=3.14.0
Requires-Dist: pillow>=9.0.0
Requires-Dist: requests>=2.28.0
Provides-Extra: dev
Requires-Dist: black>=23.0.0; extra == 'dev'
Requires-Dist: django-stubs>=4.2.0; extra == 'dev'
Requires-Dist: djangorestframework-stubs>=3.14.0; extra == 'dev'
Requires-Dist: flake8>=6.0.0; extra == 'dev'
Requires-Dist: isort>=5.12.0; extra == 'dev'
Requires-Dist: mypy>=1.0.0; extra == 'dev'
Requires-Dist: pytest-cov>=4.0.0; extra == 'dev'
Requires-Dist: pytest-django>=4.5.0; extra == 'dev'
Requires-Dist: pytest>=7.0.0; extra == 'dev'
Requires-Dist: ruff>=0.1.0; extra == 'dev'
Provides-Extra: docs
Requires-Dist: mkdocs-material>=9.0.0; extra == 'docs'
Requires-Dist: mkdocs>=1.4.0; extra == 'docs'
Requires-Dist: mkdocstrings[python]>=0.20.0; extra == 'docs'
Provides-Extra: test
Requires-Dist: factory-boy>=3.2.0; extra == 'test'
Requires-Dist: pytest-cov>=4.0.0; extra == 'test'
Requires-Dist: pytest-django>=4.5.0; extra == 'test'
Requires-Dist: pytest>=7.0.0; extra == 'test'
Requires-Dist: responses>=0.23.0; extra == 'test'
